freespans/__init__.py
freespans/aquisitions.py
freespans/kernels.py
freespans/models.py
freespans/optimal_design.py
freespans/plots.py
freespans/predict.py
freespans/simulate.py
freespans/types.py
freespans/utils.py
FreeSpans-0.1.1.dist-info/METADATA
FreeSpans-0.1.1.dist-info/WHEEL
FreeSpans-0.1.1.dist-info/top_level.txt
FreeSpans-0.1.1.dist-info/RECORD
